telega_megaimport/__init__.py
telega_megaimport/columns.py
telega_megaimport/models.py
telega_megaimport/parser.py
telega_megaimport/utils.py
telega_megaimport/management/__init__.py
telega_megaimport/management/commands/__init__.py
telega_megaimport/management/commands/create_parser.py
telega_megaimport/tests/__init__.py
telega_megaimport/tests/models.py
telega_megaimport/tests/test_columns.py
telega_megaimport/tests/test_parser_creation.py
telega_megaimport-0.7.2.dist-info/DESCRIPTION.rst
telega_megaimport-0.7.2.dist-info/METADATA
telega_megaimport-0.7.2.dist-info/RECORD
telega_megaimport-0.7.2.dist-info/WHEEL
telega_megaimport-0.7.2.dist-info/metadata.json
telega_megaimport-0.7.2.dist-info/top_level.txt
