Metadata-Version: 2.0
Name: telega-megaimport
Version: 0.7.2
Summary: Django app for creating parsers
Home-page: http://github.com/django-stars/telega-mega-import
Author: Andrew Liashchuk @ DjangoStars
Author-email: andrew.luashchuk@djangostars.com
License: MIT
Keywords: import csv xls xlsx django
Platform: UNKNOWN
Classifier: Development Status :: 4 - Beta
Classifier: License :: OSI Approved :: MIT License
Classifier: Programming Language :: Python :: 2.7
Classifier: Topic :: Software Development :: Code Generators
Classifier: Topic :: Database
Classifier: Topic :: Office/Business
Classifier: Framework :: Django
Requires-Dist: Django (>=1.7)
Requires-Dist: xlrd
Requires-Dist: python-dateutil
